opencommerce_sdk/__init__.py
opencommerce_sdk/toolkit.py
opencommerce_sdk-1.1.2.dist-info/LICENSE
opencommerce_sdk-1.1.2.dist-info/METADATA
opencommerce_sdk-1.1.2.dist-info/WHEEL
opencommerce_sdk-1.1.2.dist-info/top_level.txt
opencommerce_sdk-1.1.2.dist-info/RECORD
