Metadata-Version: 2.1
Name: opencommerce-sdk
Version: 1.1.2
Summary: SDK for AI agents to interact with services and external tools via real-time, on-demand calls
Author-email: Your Name <idan@opencommerce.xyz>
Project-URL: Homepage, https://github.com/yourusername/opencommerce-sdk
Project-URL: Bug Tracker, https://github.com/yourusername/opencommerce-sdk/issues
Classifier: Programming Language :: Python :: 3
Classifier: License :: OSI Approved :: MIT License
Classifier: Operating System :: OS Independent
Requires-Python: >=3.7
License-File: LICENSE
